{
	"name": "create_sp_trip_processed",
	"properties": {
		"folder": {
			"name": "dw_serverless/create_external_objects_processed"
		},
		"content": {
			"query": "USE NYC_Taxi_Serverless\nGO\n\nCREATE OR ALTER PROCEDURE Processed.InsertVendor\n\nAS\n\nBEGIN\n\n    -- Trip Partitioned\n    DROP VIEW IF EXISTS Processed.View_TripPartitioned\n    GO\n\n    CREATE VIEW Processed.View_TripPartitioned\n    AS\n        SELECT\n            *\n        FROM\n            OPENROWSET (\n                BULK 'trip_partitioned/**'\n                ,DATA_SOURCE = 'NYC_Taxi_Processed'\n                ,FORMAT = 'PARQUET'\n            )\n\n                WITH (\n                    PartitionYear           VARCHAR(4)\n                    ,PartitionMonth         VARCHAR(2)\n                    ,VendorID\t            TINYINT         \n                    ,PickupDateTime     \tDATETIME2(0)    \n                    ,DropoffDateTime    \tDATETIME2(0)    \n                    ,StoreFwdFlag   \t    VARCHAR(10)     \n                    ,RateCodeID\t            SMALLINT        \n                    ,PULocationID\t        SMALLINT        \n                    ,DOLocationID\t        SMALLINT        \n                    ,PassengerCount \t    TINYINT         \n                    ,TripDistance\t        FLOAT           \n                    ,FareAmount \t        FLOAT           \n                    ,Extra\t                FLOAT           \n                    ,MTATax \t            FLOAT           \n                    ,TipAmount\t            FLOAT           \n                    ,TollsAmount\t        FLOAT           \n                    ,eHailFee\t            VARCHAR(50)     \n                    ,ImprovementSurcharge   FLOAT           \n                    ,TotalAmount\t        FLOAT           \n                    ,PaymentType\t        BIGINT          \n                    ,TripType               BIGINT          \n                    ,CongestionSurcharge    FLOAT           \n                ) AS TripPartitioned\n    GO\n\nEND;",
			"metadata": {
				"language": "sql"
			},
			"currentConnection": {
				"databaseName": "NYC_Taxi_Serverless",
				"poolName": "Built-in"
			},
			"resultLimit": 5000
		},
		"type": "SqlQuery"
	}
}